Metadata-Version: 2.1
Name: adstex
Version: 0.5.0
Summary: Find all citation keys in your LaTeX documents and search NASA ADS to generate corresponding bibtex entries.
Home-page: https://github.com/yymao/adstex
Download-URL: https://github.com/yymao/adstex/archive/v0.5.0.tar.gz
Author: Yao-Yuan Mao
Author-email: yymao.astro@gmail.com
Maintainer: Yao-Yuan Mao
Maintainer-email: yymao.astro@gmail.com
License: MIT
Keywords: bibtex ads
Classifier: Environment :: Console
Classifier: Intended Audience :: End Users/Desktop
Classifier: Intended Audience :: Science/Research
Classifier: License :: OSI Approved :: MIT License
Classifier: Programming Language :: Python :: 3.7
Classifier: Programming Language :: Python :: 3.8
Classifier: Programming Language :: Python :: 3.9
Classifier: Programming Language :: Python :: 3.10
Classifier: Topic :: Scientific/Engineering :: Astronomy
License-File: LICENSE
